{
  "people": [
    {"id": "Jeff Sessions", "title":"Attorney General", "institution": "White House"},
    {"id": "James Mattis", "title":"Defense Secretary", "institution": "White House"},
    {"id": "Steven Mnuchin", "title":"Treasury Secretary", "institution": "White House"},
    {"id": "Rex W. Tillerson", "title":"Secretary of State", "institution": "White House"},
    {"id": "Stephen K. Bannon", "title":"Chief Strategist", "institution": "White House"},
    {"id": "Reince Priebus", "title":"Chief of Staff", "institution": "White House"},
    {"id": "Ryan Zinke", "title":"Interior Secretary", "institution": "White House"}
  ],
  "employments": [
    {"person": "Stephen K. Bannon", "institution": "Breitbart"}
  ],
  "institutions": [
    {"id": "Breitbart", "linkColor":"red", "color": "red", "textColor":"white", "textShadowColor":"black"},
    {"id": "White House", "linkColor":"gray", "textColor":"white", "textShadowColor":"black", "useImageFileFill":true}
  ]
}
